MLDatasetBuilder/__init__.py
MLDatasetBuilder/image_process.py
MLDatasetBuilder-1.0.0.dist-info/LICENSE.txt
MLDatasetBuilder-1.0.0.dist-info/METADATA
MLDatasetBuilder-1.0.0.dist-info/WHEEL
MLDatasetBuilder-1.0.0.dist-info/top_level.txt
MLDatasetBuilder-1.0.0.dist-info/RECORD
