Metadata-Version: 2.1
Name: MLDatasetBuilder
Version: 1.0.0
Summary: MLDatasetBuilder is a python package which is helping to prepare the image for your ML dataset.
Home-page: https://github.com/karthick965938/ML-Dataset-Builder
Author: Karthick Nagarajan
Author-email: karthick965938@gmail.com
License: MIT
Keywords: image data datascience imagedataset preparedataset prepareimage dataset mldataset datasetbuilder mldatasetbuilder ML ml machinelearning AI ai
Platform: UNKNOWN
Classifier: Programming Language :: Python :: 3
Classifier: License :: OSI Approved :: MIT License
Classifier: Operating System :: OS Independent
Requires-Python: >=3.6
Requires-Dist: opencv-python
Requires-Dist: Pillow
Requires-Dist: art
Requires-Dist: termcolor
Requires-Dist: progress
Requires-Dist: pytest
